bigQueryExporter/BigQueryExporter.py
bigQueryExporter/BigQueryExporterEnhanced.py
bigQueryExporter/___test.py
bigQueryExporter/__init__.py
bigQueryExporter/test.py
bigQueryExporterEnhanced-1.0.8.dist-info/METADATA
bigQueryExporterEnhanced-1.0.8.dist-info/RECORD
bigQueryExporterEnhanced-1.0.8.dist-info/WHEEL
bigQueryExporterEnhanced-1.0.8.dist-info/top_level.txt
