Metadata-Version: 2.1
Name: bigQueryExporterEnhanced
Version: 1.0.8
Summary: Package codes to execute queries on BQ and save to local machine, to BQ table or to GCS.
Home-page: https://github.com/tsangkinhoi/bigQueryExporter-enhanced
Author: Icarus So (enhanced by Jason Tsang)
Author-email: tsangkinhoi@gmail.com
License: UNKNOWN
Keywords: bigquery,local,export
Platform: UNKNOWN
Classifier: Programming Language :: Python :: 3
Classifier: License :: OSI Approved :: MIT License
Classifier: Operating System :: OS Independent
Requires-Dist: google-cloud-bigquery (==1.*)
Requires-Dist: google-cloud-storage (==1.*)
Requires-Dist: pandas
